{
    "AbgG":"abgg",
    "AGG":"agg",
    "AktG":"aktg",
    "AnfG":"anfg_1999",
    "AO":"ao_1977",
    "ArbGG":"arbgg",
    "BauGB":"bbaug",
    "BauNVO":"baunvo",
    "BBG":"bbg_2009",
    "BBodSchG":"bbodschg",
    "BBodSchV":"bbodschv_2023",
    "BeamtStG":"beamtstg",
    "BetrVG":"betrvg",
    "BeurkG":"beurkg",
    "BGB":"bgb",
    "BImSchG":"bimschg",
    "BMinG":"bming",
    "BPolG":"bgsg_1994",
    "BUrlG":"burlg",
    "BVerfGG":"bverfgg",
    "BWahlG":"bwahlg",
    "EGBGB":"bgbeg",
    "EGGVG":"gvgeg",
    "EGStGB":"stgbeg",
    "EGStPO":"stpoeg",
    "EntgFG":"entgfg",
    "EntgeltFG":"entgfg",
    "EGFZG":"entgfg",
    "FamFG":"famfg",
    "FZV":"fzv_2023",
    "GastG":"gastg",
    "GaststättenG":"gast",
    "GBO":"gbo",
    "GenG":"geng",
    "GewO":"gewo",
    "GG":"gg",
    "GKG":"gkg_2004",
    "GVG":"gvg",
    "HaftPflG":"haftpflg",
    "HGB":"hgb",
    "IFG":"ifg",
    "InsO":"inso",
    "InsVV":"insvv",
    "JGG":"jgg",
    "JuSchG":"juschg",
    "KSchG":"kschg"
}